aliyunsdkeds_user/__init__.py
aliyunsdkeds_user/endpoint.py
aliyunsdkeds_user/request/__init__.py
aliyunsdkeds_user/request/v20210308/BatchSetDesktopManagerRequest.py
aliyunsdkeds_user/request/v20210308/ChangeUserPasswordRequest.py
aliyunsdkeds_user/request/v20210308/CheckUsedPropertyRequest.py
aliyunsdkeds_user/request/v20210308/CheckUsedPropertyValueRequest.py
aliyunsdkeds_user/request/v20210308/CreateGroupRequest.py
aliyunsdkeds_user/request/v20210308/CreateOrgRequest.py
aliyunsdkeds_user/request/v20210308/CreatePropertyRequest.py
aliyunsdkeds_user/request/v20210308/CreateResourceGroupRequest.py
aliyunsdkeds_user/request/v20210308/CreateUsersRequest.py
aliyunsdkeds_user/request/v20210308/DeleteResourceGroupRequest.py
aliyunsdkeds_user/request/v20210308/DeleteUserPropertyValueRequest.py
aliyunsdkeds_user/request/v20210308/DescribeGroupUserRequest.py
aliyunsdkeds_user/request/v20210308/DescribeGroupsRequest.py
aliyunsdkeds_user/request/v20210308/DescribeMfaDevicesRequest.py
aliyunsdkeds_user/request/v20210308/DescribeOrgByLayerRequest.py
aliyunsdkeds_user/request/v20210308/DescribeOrgsRequest.py
aliyunsdkeds_user/request/v20210308/DescribeResourceGroupsRequest.py
aliyunsdkeds_user/request/v20210308/DescribeUsersRequest.py
aliyunsdkeds_user/request/v20210308/FilterUsersRequest.py
aliyunsdkeds_user/request/v20210308/GetManagerInfoByAuthCodeRequest.py
aliyunsdkeds_user/request/v20210308/InitTenantAliasRequest.py
aliyunsdkeds_user/request/v20210308/ListPropertyRequest.py
aliyunsdkeds_user/request/v20210308/ListPropertyValueRequest.py
aliyunsdkeds_user/request/v20210308/LockMfaDeviceRequest.py
aliyunsdkeds_user/request/v20210308/LockUsersRequest.py
aliyunsdkeds_user/request/v20210308/ModifyGroupRequest.py
aliyunsdkeds_user/request/v20210308/ModifyOrgRequest.py
aliyunsdkeds_user/request/v20210308/ModifyUserRequest.py
aliyunsdkeds_user/request/v20210308/MoveOrgRequest.py
aliyunsdkeds_user/request/v20210308/MoveUserOrgRequest.py
aliyun_python_sdk_eds_user-1.0.2.dist-info/LICENSE
aliyun_python_sdk_eds_user-1.0.2.dist-info/METADATA
aliyun_python_sdk_eds_user-1.0.2.dist-info/WHEEL
aliyun_python_sdk_eds_user-1.0.2.dist-info/top_level.txt
aliyun_python_sdk_eds_user-1.0.2.dist-info/RECORD
